qiyi_ctv_memory/Adb.py
qiyi_ctv_memory/Utils.py
qiyi_ctv_memory/__init__.py
qiyi_ctv_memory/apm_memory.py
qiyi_ctv_memory/error.py
qiyi_ctv_memory/monkey_memory.py
qiyi_ctv_memory/test.py
qiyi_ctv_memory/java/__init__.py
qiyi_ctv_memory/java/heap_analyzer.jar
qiyi_ctv_memory/java/javaHeap.py
qiyi_ctv_memory/native/__init__.py
qiyi_ctv_memory/native/native_memory.py
qiyi_ctv_memory/native/native_memory_utils.py
qiyi_ctv_memory/native/record_compare.py
qiyi_ctv_memory/native/record_end.py
qiyi_ctv_memory/native/record_start.py
qiyi_ctv_memory/native/record_summary.py
qiyi_ctv_memory/native/snapshot_check.py
qiyi_ctv_memory/native/snapshot_compare.py
qiyi_ctv_memory/native/snapshot_get.py
qiyi_ctv_memory/native/snapshot_summary.py
qiyi_ctv_memory/native/snapshots_avg.py
qiyi_ctv_memory/native/snapshots_leak_detect.py
qiyi_ctv_memory-0.1.37.dist-info/METADATA
qiyi_ctv_memory-0.1.37.dist-info/WHEEL
qiyi_ctv_memory-0.1.37.dist-info/entry_points.txt
qiyi_ctv_memory-0.1.37.dist-info/top_level.txt
qiyi_ctv_memory-0.1.37.dist-info/RECORD
